foxysafe/__init__.py
foxysafe/entrypoints.py
foxysafe/custom_hydra_plugins/__init__.py
foxysafe/custom_hydra_plugins/resolvers.py
foxysafe/git/__init__.py
foxysafe/git/clone.py
foxysafe/gitlab/__init__.py
foxysafe/gitlab/api.py
foxysafe/gitlab/backups.py
foxysafe/gitlab/download.py
foxysafe/utils/__init__.py
foxysafe/utils/custom_logging.py
foxysafe-0.1.5.dist-info/LICENSE
foxysafe-0.1.5.dist-info/METADATA
foxysafe-0.1.5.dist-info/WHEEL
foxysafe-0.1.5.dist-info/entry_points.txt
foxysafe-0.1.5.dist-info/top_level.txt
foxysafe-0.1.5.dist-info/RECORD
