Metadata-Version: 2.1
Name: foxysafe
Version: 0.1.5
Summary: GitLab backup tool.
License: MIT
Project-URL: Homepage, https://github.com/Pythoniasm/foxysafe
Requires-Python: >=3.12.1
License-File: LICENSE
Requires-Dist: beartype ==0.14.1
Requires-Dist: GitPython ==3.1.41
Requires-Dist: hydra-core ==1.3.2
Requires-Dist: loguru ==0.7.0
Requires-Dist: pyshortcuts ==1.9.0
Requires-Dist: python-dotenv ==1.0.0
Requires-Dist: python-gitlab ==3.15.0
Requires-Dist: rich ==13.4.1
Requires-Dist: selenium ==4.17.2
Requires-Dist: tqdm ==4.56.0
Requires-Dist: webdriver-manager ==4.0.1
Provides-Extra: dev
Requires-Dist: black ==24.2.0 ; extra == 'dev'
Requires-Dist: build ==1.0.3 ; extra == 'dev'
Requires-Dist: isort ==5.13.2 ; extra == 'dev'
Requires-Dist: pipdeptree ==2.7.1 ; extra == 'dev'
Requires-Dist: ruff ==0.2.2 ; extra == 'dev'
Requires-Dist: twine ==4.0.2 ; extra == 'dev'
